Metadata-Version: 1.0
Name: lyrics-dl
Version: 1.1.1
Summary: A tool to obtain the lyrics to your favorite songs
Home-page: https://github.com/gauthamk97/getlyrics
Author: Gautham Kumar
Author-email: kgautham1997@gmail.com
License: MIT
Platform: UNKNOWN
